DataStructuresAndObjectOrientedDesignLectureNotesUscCsci104/README.md
DataStructuresAndObjectOrientedDesignLectureNotesUscCsci104/__init__.py
DataStructuresAndObjectOrientedDesignLectureNotesUscCsci104/__main__.py
DataStructuresAndObjectOrientedDesignLectureNotesUscCsci104/file.pdf
DataStructuresAndObjectOrientedDesignLectureNotesUscCsci104/index.html
data_structures_and_object_oriented_design_lecture_notes_usc_csci104-2024.3.2.0.dist-info/METADATA
data_structures_and_object_oriented_design_lecture_notes_usc_csci104-2024.3.2.0.dist-info/WHEEL
data_structures_and_object_oriented_design_lecture_notes_usc_csci104-2024.3.2.0.dist-info/entry_points.txt
data_structures_and_object_oriented_design_lecture_notes_usc_csci104-2024.3.2.0.dist-info/top_level.txt
data_structures_and_object_oriented_design_lecture_notes_usc_csci104-2024.3.2.0.dist-info/RECORD
